[
  {
    "title": "【緊急開催】(株)関西デジタル オンライン説明会",
    "start": "2025-12-10",
    "url": "https://www.kokuchpro.com/",
    "color": "#EF4444",
    "description": "これはダミーデータです。スクレイピングがブロックされました。"
  },
  {
    "title": "【緊急開催】ネクストイノベーション オンライン説明会",
    "start": "2025-12-11",
    "url": "https://www.kokuchpro.com/",
    "color": "#EF4444",
    "description": "これはダミーデータです。スクレイピングがブロックされました。"
  },
  {
    "title": "【緊急開催】大阪ITソリューションズ オンライン説明会",
    "start": "2025-12-11",
    "url": "https://www.kokuchpro.com/",
    "color": "#EF4444",
    "description": "これはダミーデータです。スクレイピングがブロックされました。"
  },
  {
    "title": "【緊急開催】(株)関西デジタル オンライン説明会",
    "start": "2025-12-08",
    "url": "https://www.kokuchpro.com/",
    "color": "#EF4444",
    "description": "これはダミーデータです。スクレイピングがブロックされました。"
  },
  {
    "title": "【緊急開催】梅田WEBサービス オンライン説明会",
    "start": "2025-12-10",
    "url": "https://www.kokuchpro.com/",
    "color": "#EF4444",
    "description": "これはダミーデータです。スクレイピングがブロックされました。"
  },
  {
    "title": "【緊急開催】(株)関西デジタル オンライン説明会",
    "start": "2025-12-09",
    "url": "https://www.kokuchpro.com/",
    "color": "#EF4444",
    "description": "これはダミーデータです。スクレイピングがブロックされました。"
  },
  {
    "title": "【緊急開催】大阪ITソリューションズ オンライン説明会",
    "start": "2025-12-11",
    "url": "https://www.kokuchpro.com/",
    "color": "#EF4444",
    "description": "これはダミーデータです。スクレイピングがブロックされました。"
  },
  {
    "title": "【緊急開催】大阪ITソリューションズ オンライン説明会",
    "start": "2025-12-11",
    "url": "https://www.kokuchpro.com/",
    "color": "#EF4444",
    "description": "これはダミーデータです。スクレイピングがブロックされました。"
  },
  {
    "title": "【緊急開催】神戸テック オンライン説明会",
    "start": "2025-12-11",
    "url": "https://www.kokuchpro.com/",
    "color": "#EF4444",
    "description": "これはダミーデータです。スクレイピングがブロックされました。"
  },
  {
    "title": "【緊急開催】大阪ITソリューションズ オンライン説明会",
    "start": "2025-12-09",
    "url": "https://www.kokuchpro.com/",
    "color": "#EF4444",
    "description": "これはダミーデータです。スクレイピングがブロックされました。"
  }
]